[{"configName":"test","dbType":"mysql","properties":{"project.dao.path":"cico-test/src/main/java/com.jiangroom.api.dao","project.entity.path":"cico-test/src/main/java/com.jiangroom.api.run","project.service.path":"cico-test/src/main/java/com.jiangroom.api.service","project.vo.path":"cico-test/src/main/java/com.jiangroom.api.run","project.path":"D:\\test\\generate","project.query.path":"cico-test/src/main/java/com.jiangroom.api.run","project.mapper.path":"cico-test/src/main/java/com.jiangroom.api.dao","project.serviceimpl.path":"cico-test/src/main/java/com.jiangroom.api.service.impl","project.author":"cico"},"used":true}]